gaussCLI/__init__.py
gaussCLI/gauss.py
gaussCLI/gaussCli.py
gaussCLI/matrixOperations.py
gaussCLI/printer.py
gauss_cli-1.0.1.dist-info/METADATA
gauss_cli-1.0.1.dist-info/WHEEL
gauss_cli-1.0.1.dist-info/top_level.txt
gauss_cli-1.0.1.dist-info/RECORD
