Metadata-Version: 2.1
Name: gauss-cli
Version: 1.0.1
Summary: gussian elimination method package
Author: messabih khalil
Author-email: msbih.khalil@gmail.com
Classifier: Programming Language :: Python :: 3
Classifier: License :: OSI Approved :: MIT License
Classifier: Operating System :: OS Independent
Requires-Dist: commonmark
Requires-Dist: numpy
Requires-Dist: rich
Requires-Dist: Pygments
